cruscopoetry/plugins/wolofalarud/__init__.py
cruscopoetry/plugins/wolofalarud/__main__.py
cruscopoetry/plugins/wolofalarud/metric_elements.py
cruscopoetry/plugins/wolofalarud/parser_classes.py
cruscopoetry/plugins/wolofalarud/renderer_class.py
cruscopoetry/plugins/wolofalarud/wolofal_constants.toml
cruscopoetry.plugins.wolofalarud-0.0.2.dist-info/METADATA
cruscopoetry.plugins.wolofalarud-0.0.2.dist-info/WHEEL
cruscopoetry.plugins.wolofalarud-0.0.2.dist-info/entry_points.txt
cruscopoetry.plugins.wolofalarud-0.0.2.dist-info/top_level.txt
cruscopoetry.plugins.wolofalarud-0.0.2.dist-info/RECORD
