Metadata-Version: 2.1
Name: cruscopoetry.plugins.wolofalarud
Version: 0.0.2
Summary: ʿArūḍ parser for wolofal poems in cruscopoetry format
Home-page: https://gitlab.com/kikulacho92/cruscopoetry_new
Author: Emiliano Minerba
Author-email: emi.nerba@gmail.com
License: GPL
Platform: UNKNOWN
Requires-Dist: cruscopoetry.plugins.cruscoarud
